komanawa/gw_detect_power/__init__.py
komanawa/gw_detect_power/base_detection_calculator.py
komanawa/gw_detect_power/change_detection_counterfactual.py
komanawa/gw_detect_power/change_detection_slope.py
komanawa/gw_detect_power/create_lookup_tables.py
komanawa/gw_detect_power/lookup_table_inits.py
komanawa/gw_detect_power/timeit_test_results.txt
komanawa/gw_detect_power/timetest_slope.py
komanawa/gw_detect_power/version.py
komanawa_gw_detect_power-2.0.2.dist-info/licenses/LICENSE
komanawa_gw_detect_power-2.0.2.dist-info/METADATA
komanawa_gw_detect_power-2.0.2.dist-info/WHEEL
komanawa_gw_detect_power-2.0.2.dist-info/top_level.txt
komanawa_gw_detect_power-2.0.2.dist-info/RECORD
