Metadata-Version: 2.4
Name: komanawa-gw-detect-power
Version: 2.0.2
Summary: A package to estimate the detection power of a groundwater monitoring network including the effects of groundwater travel processes (lag), sampling noise, and other unexplained sample varience.
Author-email: Matt Dumont <Matt@komanawa.com>
License:                    GNU LESSER GENERAL PUBLIC LICENSE
Project-URL: Homepage, https://github.com/Komanawa-Solutions-Ltd/komanawa-gw-detect-power
Project-URL: Issues, https://github.com/Komanawa-Solutions-Ltd/komanawa-gw-detect-power/issues
Project-URL: Documentation, https://komanawa-solutions-ltd.github.io/komanawa-gw-detect-power/
Classifier: Programming Language :: Python :: 3
Classifier: License :: OSI Approved :: GNU Lesser General Public License v3 or later (LGPLv3+)
Classifier: Operating System :: OS Independent
Requires-Python: >=3.11
License-File: LICENSE
Requires-Dist: pandas>=2.0.3
Requires-Dist: numpy>=1.25.2
Requires-Dist: scipy>=1.11.2
Requires-Dist: tables>=3.8.0
Requires-Dist: psutil>=5.9.5
Requires-Dist: komanawa-kendall-stats>=2.0.3
Requires-Dist: komanawa-gw-age-tools>=2.1.2
Requires-Dist: pyhomogeneity>=1.1.0
Dynamic: license-file
